pybatchexecute/__init__.py
pybatchexecute/decode.py
pybatchexecute/encode.py
pybatchexecute/test_decode.py
pybatchexecute/test_encode.py
pybatchexecute-1.0.0.dist-info/LICENSE
pybatchexecute-1.0.0.dist-info/METADATA
pybatchexecute-1.0.0.dist-info/WHEEL
pybatchexecute-1.0.0.dist-info/top_level.txt
pybatchexecute-1.0.0.dist-info/RECORD
