Metadata-Version: 2.1
Name: pybatchexecute
Version: 1.0.0
Summary: Library to ease interactions with Google's batchexecute batch RPC system
Author-email: Pierre Nicolas Durette <pndurette@gmail.com>
License: MIT
Project-URL: homepage, https://github.com/pndurette/pybatchexecute
Project-URL: documentation, https://github.com/pndurette/pybatchexecute/blob/main/docs/README.md
Project-URL: repository, https://github.com/pndurette/pybatchexecute
Project-URL: changelog, https://github.com/pndurette/pybatchexecute/blob/main/CHANGELOG.md
Requires-Python: >=3.8
License-File: LICENSE
Provides-Extra: docs
Requires-Dist: pydoc-markdown (~=4.6) ; extra == 'docs'
Provides-Extra: test
Requires-Dist: pytest (<7.4.0,>=7.1.3) ; extra == 'test'
